gha_workflow_linter/__init__.py
gha_workflow_linter/_version.py
gha_workflow_linter/auto_fix.py
gha_workflow_linter/cache.py
gha_workflow_linter/cli.py
gha_workflow_linter/config.py
gha_workflow_linter/exceptions.py
gha_workflow_linter/git_validator.py
gha_workflow_linter/github_api.py
gha_workflow_linter/github_auth.py
gha_workflow_linter/models.py
gha_workflow_linter/patterns.py
gha_workflow_linter/py.typed
gha_workflow_linter/scanner.py
gha_workflow_linter/system_utils.py
gha_workflow_linter/utils.py
gha_workflow_linter/validator.py
gha_workflow_linter-1.0.2.dist-info/METADATA
gha_workflow_linter-1.0.2.dist-info/WHEEL
gha_workflow_linter-1.0.2.dist-info/entry_points.txt
gha_workflow_linter-1.0.2.dist-info/licenses/LICENSE
gha_workflow_linter-1.0.2.dist-info/RECORD
