Metadata-Version: 2.4
Name: gha-workflow-linter
Version: 1.0.2
Summary: GitHub Actions workflow linter for validating action and workflow calls
Project-URL: Homepage, https://github.com/lfit/gha-workflow-linter
Project-URL: Documentation, https://gha-workflow-linter.readthedocs.io
Project-URL: Repository, https://github.com/lfit/gha-workflow-linter.git
Project-URL: Bug Tracker, https://github.com/lfit/gha-workflow-linter/issues
Project-URL: Changelog, https://github.com/lfit/gha-workflow-linter/releases
Author-email: The Linux Foundation <releng@linuxfoundation.org>
License: Apache-2.0
License-File: LICENSE
Keywords: actions,github,linting,validation,workflows
Classifier: Development Status :: 4 - Beta
Classifier: Environment :: Console
Classifier: Intended Audience :: Developers
Classifier: License :: OSI Approved :: Apache Software License
Classifier: Operating System :: OS Independent
Classifier: Programming Language :: Python :: 3
Classifier: Programming Language :: Python :: 3.10
Classifier: Programming Language :: Python :: 3.11
Classifier: Programming Language :: Python :: 3.12
Classifier: Programming Language :: Python :: 3.13
Classifier: Programming Language :: Python :: 3.14
Classifier: Topic :: Software Development :: Quality Assurance
Classifier: Topic :: Software Development :: Testing
Requires-Python: >=3.10
Requires-Dist: httpx>=0.28.1
Requires-Dist: pydantic-settings>=2.12.0
Requires-Dist: pydantic>=2.12.5
Requires-Dist: pyyaml>=6.0.2
Requires-Dist: rich>=14.2.0
Requires-Dist: typer>=0.21.1
Requires-Dist: typing-extensions>=4.12.0
Provides-Extra: dev
Requires-Dist: mypy>=1.19.1; extra == 'dev'
Requires-Dist: pre-commit>=4.5.1; extra == 'dev'
Requires-Dist: pytest-asyncio>=0.25.0; extra == 'dev'
Requires-Dist: pytest-cov>=6.0.0; extra == 'dev'
Requires-Dist: pytest-mock>=3.14.0; extra == 'dev'
Requires-Dist: pytest>=9.0.2; extra == 'dev'
Requires-Dist: ruff>=0.14.10; extra == 'dev'
Requires-Dist: types-pyyaml>=6.0.12.20241230; extra == 'dev'
